{
  "$schema": "../../specs/erc7730-v2.schema.json",
  "context": {
    "$id": "DistributionToDelegators-Flare",
    "contract": { "deployments": [{ "chainId": 14, "address": "0x9c7A4C83842B29bB4A082b0E689CB9474BD938d0" }] }
  },
  "metadata": { "owner": "Flare Labs", "info": { "url": "https://flare.network/" }, "contractName": "DistributionToDelegators-Flare" },
  "display": {
    "formats": {
      "claim(address _rewardOwner, address _recipient, uint256 _month, bool _wrap)": {
        "intent": "claim rewards",
        "fields": [
          {
            "label": "Reward Owner",
            "format": "addressName",
            "params": { "types": ["eoa", "wallet"] },
            "path": "#._rewardOwner",
            "visible": "always"
          },
          {
            "label": "Recipient",
            "format": "addressName",
            "params": { "types": ["eoa", "wallet"] },
            "path": "#._recipient",
            "visible": "always"
          },
          { "label": "Month", "format": "raw", "path": "#._month", "visible": "always" },
          { "label": "Wrap", "format": "raw", "path": "#._wrap", "visible": "always" }
        ]
      },
      "autoClaim(address[] _rewardOwners, uint256 _month)": {
        "intent": "batch claims rewards",
        "fields": [
          {
            "label": "Reward Owner",
            "format": "addressName",
            "params": { "types": ["eoa", "wallet"] },
            "path": "#._rewardOwners.[]",
            "visible": "always"
          },
          { "label": "Month", "format": "raw", "path": "#._month", "visible": "always" }
        ]
      },
      "confirmOptOutOfAirdrop(address[] _optOutAddresses)": {
        "intent": "opt out of airdrop",
        "fields": [
          {
            "label": "Opt Out Address",
            "format": "addressName",
            "params": { "types": ["wallet", "eoa", "contract", "token", "collection"] },
            "path": "#._optOutAddresses.[]",
            "visible": "always"
          }
        ]
      }
    }
  }
}
