{
  "$schema": "../../specs/erc7730-v2.schema.json",
  "metadata": {
    "owner": "Yield.xyz",
    "info": { "url": "https://yield.xyz/" },
    "constants": { "underlyingToken": "0x4c9EDD5852cd905f086C759E8383e09bff1E68B3", "underlyingTicker": "USDe", "vaultTicker": "stk-USDe" }
  },
  "context": { "contract": { "deployments": [{ "chainId": 1, "address": "0x2D152fB171353E70e45322D32bC748F8a61d9971" }] } },
  "display": {
    "formats": {
      "deposit(uint256 _underlying, address receiver)": {
        "intent": "Deposit",
        "fields": [
          {
            "path": "_underlying",
            "label": "Deposit asset",
            "format": "tokenAmount",
            "params": { "token": "$.metadata.constants.underlyingToken" },
            "visible": "always"
          },
          { "label": "Share ticker", "format": "raw", "value": "$.metadata.constants.vaultTicker" },
          {
            "path": "receiver",
            "label": "Send shares to",
            "format": "addressName",
            "params": { "types": ["eoa", "contract"] },
            "visible": "always"
          }
        ]
      },
      "mint(uint256 shares, address receiver)": {
        "intent": "Mint",
        "fields": [
          { "label": "Deposit asset", "format": "raw", "value": "$.metadata.constants.underlyingTicker" },
          {
            "path": "shares",
            "label": "Minted shares",
            "format": "tokenAmount",
            "params": { "tokenPath": "@.to" },
            "visible": "always"
          },
          {
            "path": "receiver",
            "label": "Mint shares to",
            "format": "addressName",
            "params": { "types": ["eoa", "contract"] },
            "visible": "always"
          }
        ]
      },
      "withdraw(uint256 _underlying, address receiver, address owner)": {
        "intent": "Withdraw",
        "fields": [
          {
            "path": "_underlying",
            "label": "Withdraw exactly",
            "format": "tokenAmount",
            "params": { "token": "$.metadata.constants.underlyingToken" },
            "visible": "always"
          },
          {
            "path": "receiver",
            "label": "To",
            "format": "addressName",
            "params": { "types": ["eoa", "contract"] },
            "visible": "always"
          },
          {
            "path": "owner",
            "label": "Owner",
            "format": "addressName",
            "params": { "types": ["eoa", "contract"] },
            "visible": "always"
          }
        ]
      },
      "redeem(uint256 shares, address receiver, address owner)": {
        "intent": "Redeem",
        "fields": [
          {
            "path": "shares",
            "label": "Shares to redeem",
            "format": "tokenAmount",
            "params": { "tokenPath": "@.to" },
            "visible": "always"
          },
          {
            "path": "receiver",
            "label": "To",
            "format": "addressName",
            "params": { "types": ["eoa", "contract"] },
            "visible": "always"
          },
          {
            "path": "owner",
            "label": "Owner",
            "format": "addressName",
            "params": { "types": ["eoa", "contract"] },
            "visible": "always"
          }
        ]
      }
    }
  }
}
