{
  "context": {
    "eip712": {
      "domain": {
        "name": "Tally",
        "chainId": 42161,
        "verifyingContract": "0xf07ded9dc292157749b6fd268e37df6ea38395b9"
      },
      "schemas": [
        {
          "primaryType": "Arbitrum Foundation: Core Governor",
          "types": {
            "Ballot": [
              {
                "name": "proposalId",
                "type": "uint256"
              },
              {
                "name": "support",
                "type": "uint8"
              }
            ],
            "EIP712Domain": [
              {
                "name": "chainId",
                "type": "uint256"
              },
              {
                "name": "name",
                "type": "string"
              },
              {
                "name": "verifyingContract",
                "type": "address"
              },
              {
                "name": "version",
                "type": "string"
              }
            ]
          }
        }
      ],
      "deployments": [
        {
          "chainId": 42161,
          "address": "0xf07ded9dc292157749b6fd268e37df6ea38395b9"
        }
      ]
    }
  },
  "metadata": {
    "owner": "L2ArbitrumGovernor"
  },
  "display": {
    "formats": {
      "Arbitrum Foundation: Core Governor": {
        "fields": [
          {
            "path": "proposalId",
            "label": "Proposal id",
            "format": "raw"
          },
          {
            "path": "support",
            "label": "Support",
            "format": "raw"
          }
        ]
      }
    }
  }
}
